mqtt_leds/__init__.py
mqtt_leds/config/loader.py
mqtt_leds/controller.py
mqtt_leds/core/color.py
mqtt_leds/core/effects.py
mqtt_leds/core/led_strip.py
mqtt_leds/effects/ws2811/hopscotch.py
mqtt_leds/effects/ws281x/__init__.py
mqtt_leds/effects/ws281x/animations.py
mqtt_leds/effects/ws281x/shapes.py
mqtt_leds/mqtt/client.py
mqtt_leds/types/solarox_rgb.py
mqtt_leds/types/ws2811.py
mqtt_leds/types/ws281x.py
mqtt_leds/utils/__init__.py
mqtt_leds/utils/colors.py
mqtt_leds/utils/coordinates.py
mqtt_leds_lib-1.0.0rc2.dist-info/METADATA
mqtt_leds_lib-1.0.0rc2.dist-info/WHEEL
mqtt_leds_lib-1.0.0rc2.dist-info/RECORD
