Metadata-Version: 2.3
Name: mqtt-leds-lib
Version: 1.0.0rc2
Summary: This library makes it possible to control many types of led strips using mqtt configured for homeassistant
License: Apache-2.0
Author: Guillaume Richard
Author-email: lord0gnome@gmail.com
Requires-Python: >=3.11,<4.0
Classifier: License :: OSI Approved :: Apache Software License
Classifier: Programming Language :: Python :: 3
Classifier: Programming Language :: Python :: 3.11
Classifier: Programming Language :: Python :: 3.12
Classifier: Programming Language :: Python :: 3.13
Requires-Dist: RPi.GPIO (>=0.7.1,<0.8.0)
Requires-Dist: adafruit-blinka (>=8.50.0,<9.0.0)
Requires-Dist: adafruit-circuitpython-neopixel (>=6.3.12,<7.0.0)
Requires-Dist: paho-mqtt (>=2.1.0,<3.0.0)
Requires-Dist: python-dotenv (>=1.0.1,<2.0.0)
Requires-Dist: pyyaml (>=6.0.2,<7.0.0)
Requires-Dist: rpi-ws281x (>=5.0.0,<6.0.0)
